CopulaSimilarity/CSM.py
CopulaSimilarity/__init__.py
similarity_metrics/__init__.py
similarity_metrics/fsim_quality.py
similarity_metrics/issm_quality.py
similarity_metrics/ssim_rmse_psnr_metrics.py
CopulaSimilarity-0.1.1.dist-info/METADATA
CopulaSimilarity-0.1.1.dist-info/WHEEL
CopulaSimilarity-0.1.1.dist-info/top_level.txt
CopulaSimilarity-0.1.1.dist-info/RECORD
