Metadata-Version: 2.1
Name: CopulaSimilarity
Version: 0.1.1
Summary: A package for locally sensitive Copula-Based Similarity Metric along with image quality metrics.
Home-page: https://github.com/safouaneelg/copulasimilarity
Author: Safouane El Ghazouali
Author-email: safouane.elghazouali@gmail.com
Classifier: Programming Language :: Python :: 3
Classifier: License :: OSI Approved :: MIT License
Classifier: Operating System :: OS Independent
Requires-Python: >=3.8
Requires-Dist: numpy ==1.24.3
Provides-Extra: full
Requires-Dist: opencv-contrib-python ==4.8.0.76 ; extra == 'full'
Requires-Dist: opencv-python ==4.8.1.78 ; extra == 'full'
Requires-Dist: opencv-python-headless ==4.7.0.72 ; extra == 'full'
Requires-Dist: phasepack ==1.5 ; extra == 'full'
Requires-Dist: scipy ==1.9.1 ; extra == 'full'
Requires-Dist: skimage ==0.0 ; extra == 'full'
Requires-Dist: image-similarity-measures ; extra == 'full'
Requires-Dist: matplotlib ; extra == 'full'
